qbs/__init__.py
qbs/conf/default_config.json
qbs-2.0.3.dist-info/LICENSE
qbs-2.0.3.dist-info/METADATA
qbs-2.0.3.dist-info/WHEEL
qbs-2.0.3.dist-info/entry_points.txt
qbs-2.0.3.dist-info/top_level.txt
qbs-2.0.3.dist-info/RECORD
