Metadata-Version: 2.1
Name: qbs
Version: 2.0.3
Summary: Quick (and dirty) build system
Home-page: https://gitlab.com/nonnymoose/qbs
Author: Nonny Moose
Author-email: moosenonny10@gmail.com
License: UNKNOWN
Platform: UNKNOWN
Classifier: Programming Language :: Python :: 3
Classifier: License :: OSI Approved :: GNU General Public License v3 (GPLv3)
Classifier: Environment :: Console
Classifier: Intended Audience :: Education
Classifier: Intended Audience :: Developers
Classifier: Operating System :: OS Independent
Classifier: Topic :: Software Development :: Build Tools
Requires-Python: >=3
